tee_selector/__init__.py
tee_selector/hole.py
tee_selector/tee.py
tee_selector/tee_manager.py
tests/test_tee_selector.py
tee_selector-0.5.0.dist-info/LICENSE
tee_selector-0.5.0.dist-info/METADATA
tee_selector-0.5.0.dist-info/WHEEL
tee_selector-0.5.0.dist-info/top_level.txt
tee_selector-0.5.0.dist-info/RECORD
